{
  "index": 726,
  "overall": 5,
  "verified": true,
  "reviewTime": "03 18, 2017",
  "reviewerID": "A25SOIZ0IZE1YY",
  "asin": "B0058YEJ5K",
  "style": {
    "Size:": " 8 B(M) US",
    "Color:": " Racer Blue/Obsidian/Blue Tint"
  },
  "reviewerName": "vp22",
  "reviewText": "I have gotten so many compliments on the blue color and look of this shoe.  It is super comfortable.  The grip is wonderful for my indoor gym cross training classes.  I always order a half size larger in Nike brand shoes and thy fit perfectly as I did with this shoe.",
  "summary": "Love These Shoes!",
  "unixReviewTime": 1489795200,
  "vote": 8.0,
  "image": "",
  "reviewed_at": "2017-03-18T00:00:00",
  "review_text_word_count": 51
}