{
  "index": 1427943,
  "overall": 1,
  "verified": true,
  "reviewTime": "09 12, 2016",
  "reviewerID": "A3C8FPW0AXGLNY",
  "asin": "B00N0W9SN0",
  "style": "",
  "reviewerName": "Yuchen",
  "reviewText": "Cheap,Ugly. Not because those beads are plastic, but all the material , especially the glass, looks cheap and ugly \nIt's cheap price I know, but it just doesn't even worth the price! I purchased another lamp just a few bucks more and looks awesome. \nNot even worth to spend time to return it.",
  "summary": "I purchased another lamp just a few bucks more and looks awesome. Not even worth to spend time to return ...",
  "unixReviewTime": 1473638400,
  "vote": "",
  "image": "",
  "reviewed_at": "2016-09-12T00:00:00",
  "review_text_word_count": 53
}